README.rst
lolcat.py
lolcommitmsg.py
setup.py
lolcommitmsg.egg-info/PKG-INFO
lolcommitmsg.egg-info/SOURCES.txt
lolcommitmsg.egg-info/dependency_links.txt
lolcommitmsg.egg-info/entry_points.txt
lolcommitmsg.egg-info/pbr.json
lolcommitmsg.egg-info/top_level.txt